kilosort/CCG.py
kilosort/__init__.py
kilosort/__main__.py
kilosort/bench.py
kilosort/clustering_qr.py
kilosort/data_tools.py
kilosort/datashift.py
kilosort/hierarchical.py
kilosort/io.py
kilosort/parameters.py
kilosort/plots.py
kilosort/postprocessing.py
kilosort/preprocessing.py
kilosort/run_kilosort.py
kilosort/simulation.py
kilosort/spikedetect.py
kilosort/swarmsplitter.py
kilosort/template_matching.py
kilosort/utils.py
kilosort/wTEMP.npz
kilosort/gui/__init__.py
kilosort/gui/converter.py
kilosort/gui/data_view_box.py
kilosort/gui/header_box.py
kilosort/gui/launch.py
kilosort/gui/logger.py
kilosort/gui/main.py
kilosort/gui/message_log_box.py
kilosort/gui/minor_gui_elements.py
kilosort/gui/palettes.py
kilosort/gui/probe_view_box.py
kilosort/gui/run_box.py
kilosort/gui/sanity_plots.py
kilosort/gui/settings_box.py
kilosort/gui/sorter.py
kilosort-4.1.5.dist-info/licenses/LICENSE
kilosort-4.1.5.dist-info/METADATA
kilosort-4.1.5.dist-info/WHEEL
kilosort-4.1.5.dist-info/top_level.txt
kilosort-4.1.5.dist-info/RECORD
