Metadata-Version: 2.4
Name: kilosort
Version: 4.1.5
Summary: spike sorting pipeline
Home-page: https://github.com/MouseLand/kilosort
Author: Marius Pachitariu
Author-email: pachitarium@janelia.hhmi.org
License: BSD
Classifier: Programming Language :: Python :: 3
Classifier: License :: OSI Approved :: GNU General Public License v3 (GPLv3)
Classifier: Operating System :: OS Independent
Requires-Python: >=3.9
License-File: LICENSE
Requires-Dist: numpy>=1.20.0
Requires-Dist: scipy
Requires-Dist: scikit-learn
Requires-Dist: tqdm
Requires-Dist: torch>=2.1.0
Requires-Dist: numba
Requires-Dist: faiss-cpu
Requires-Dist: psutil
Requires-Dist: matplotlib
Provides-Extra: docs
Requires-Dist: sphinx>=3.0; extra == "docs"
Requires-Dist: sphinxcontrib-apidoc; extra == "docs"
Requires-Dist: nbsphinx; extra == "docs"
Requires-Dist: myst_parser; extra == "docs"
Requires-Dist: sphinx_rtd_theme; extra == "docs"
Requires-Dist: pandoc; extra == "docs"
Provides-Extra: gui
Requires-Dist: pyqtgraph>=0.13.0; extra == "gui"
Requires-Dist: qtpy; extra == "gui"
Requires-Dist: pyqt6; extra == "gui"
Requires-Dist: pyqt6.sip; extra == "gui"
Provides-Extra: all
Requires-Dist: pyqtgraph>=0.13.0; extra == "all"
Requires-Dist: qtpy; extra == "all"
Requires-Dist: pyqt6; extra == "all"
Requires-Dist: pyqt6.sip; extra == "all"
Dynamic: author
Dynamic: author-email
Dynamic: classifier
Dynamic: description
Dynamic: description-content-type
Dynamic: home-page
Dynamic: license
Dynamic: license-file
Dynamic: provides-extra
Dynamic: requires-dist
Dynamic: requires-python
Dynamic: summary
